sdswrapper/__init__.py
sdswrapper/models.py
sdswrapper/ordinarykriginginterface.py
sdswrapper/parameters.py
sdswrapper/sampler.py
sdswrapper/wrapper.py
sdswrapper/utils/utils.py
sdswrapper-0.2.11.dist-info/METADATA
sdswrapper-0.2.11.dist-info/WHEEL
sdswrapper-0.2.11.dist-info/top_level.txt
sdswrapper-0.2.11.dist-info/RECORD
