Metadata-Version: 2.1
Name: sdswrapper
Version: 0.2.11
Summary: A Python package for spatial data science workflows.
Home-page: https://github.com/AndersonEduardo/sdswrapper
Author: Anderson Aires Eduardo
Author-email: andersonaed@gmail.com
Classifier: Programming Language :: Python :: 3
Classifier: License :: OSI Approved :: MIT License
Classifier: Operating System :: OS Independent
Requires-Python: >=3.7
Requires-Dist: numpy
Requires-Dist: pandas
Requires-Dist: matplotlib
Requires-Dist: scikit-learn
Requires-Dist: pykrige
